shotwell_mover/__init__.py
shotwell_mover/cli.py
shotwell_mover-0.2.0.dist-info/entry_points.txt
shotwell_mover-0.2.0.dist-info/LICENSE
shotwell_mover-0.2.0.dist-info/WHEEL
shotwell_mover-0.2.0.dist-info/METADATA
shotwell_mover-0.2.0.dist-info/RECORD
